[
  {
    "id": 6,
    "name": "Peach empanada",
    "picture": "https://images.unsplash.com/photo-1532704868953-d85f24176d73?ixid=MnwxMjA3fDB8MHxwaG90by1wYWdlfHx8fGVufDB8fHx8&ixlib=rb-1.2.1",
    "description": "Easy light lunch from juicy peaches."
  },
  {
    "id": 7,
    "name": "Steak with vegetables",
    "picture": "https://images.unsplash.com/photo-1544025162-d76694265947?ixid=MnwxMjA3fDB8MHxwaG90by1wYWdlfHx8fGVufDB8fHx8&ixlib=rb-1.2.1",
    "description": "Tasty steak with a load of season vegetables."
  },
  {
    "id": 8,
    "name": "Summer brunch",
    "picture": "https://images.unsplash.com/photo-1504754524776-8f4f37790ca0?ixid=MnwxMjA3fDB8MHxwaG90by1wYWdlfHx8fGVufDB8fHx8&ixlib=rb-1.2.1",
    "description": "A variety of easy to cook snacks for a summer brunch."
  },
  {
    "id": 9,
    "name": "Chips",
    "picture": "https://images.unsplash.com/photo-1599490659213-e2b9527bd087?ixid=MnwxMjA3fDB8MHxwaG90by1wYWdlfHx8fGVufDB8fHx8&ixlib=rb-1.2.1",
    "description": "Healthy snack with a bit of cheese."
  },
  {
    "id": 10,
    "name": "Apple juice",
    "picture": "https://images.unsplash.com/photo-1560806887-1e4cd0b6cbd6?ixid=MnwxMjA3fDB8MHxwaG90by1wYWdlfHx8fGVufDB8fHx8&ixlib=rb-1.2.1",
    "description": "Fresh easy to cook healthy alternative for sweet beverages."
  },
  {
    "id": 1,
    "name": "Crunchy croissants",
    "picture": "https://images.unsplash.com/photo-1555507036-ab1f4038808a?ixid=MnwxMjA3fDB8MHxwaG90by1wYWdlfHx8fGVufDB8fHx8&ixlib=rb-1.2.1",
    "description": "Buttery, flaky pastry named for its crescent shape."
  },
  {
    "id": 2,
    "name": "Grilled eggplant",
    "picture": "https://images.unsplash.com/photo-1591813144634-eebdeab865e1?ixid=MnwxMjA3fDB8MHxwaG90by1wYWdlfHx8fGVufDB8fHx8&ixlib=rb-1.2.1",
    "description": "Tender with a rich, complex flavor when cooked."
  },
  {
    "id": 3,
    "name": "Tangerine salad",
    "picture": "https://images.unsplash.com/photo-1482012792084-a0c3725f289f?ixid=MnwxMjA3fDB8MHxwaG90by1wYWdlfHx8fGVufDB8fHx8&ixlib=rb-1.2.1",
    "description": "Peak tangerine season lasts from autumn to spring."
  },
  {
    "id": 4,
    "name": "Pomegranate juice",
    "picture": "https://images.unsplash.com/photo-1606914998137-d9b33982be02?ixid=MnwxMjA3fDB8MHxwaG90by1wYWdlfHx8fGVufDB8fHx8&ixlib=rb-1.2.1",
    "description": "A superfood for a good skin, hair and health."
  },
  {
    "id": 5,
    "name": "Chili salsa",
    "picture": "https://images.unsplash.com/photo-1599297915243-ba242cff4073?ixid=MnwxMjA3fDB8MHxwaG90by1wYWdlfHx8fGVufDB8fHx8&ixlib=rb-1.2.1",
    "description": "Heat up any taco night with minimal preparation."
  }
]
